saffire/__init__.py
saffire/__main__.py
saffire/py.typed
saffire-0.0.0.dist-info/entry_points.txt
saffire-0.0.0.dist-info/LICENSE
saffire-0.0.0.dist-info/WHEEL
saffire-0.0.0.dist-info/METADATA
saffire-0.0.0.dist-info/RECORD
