Metadata-Version: 2.1
Name: saffire
Version: 0.0.0
Summary: Saffire
Home-page: https://github.com/csala/saffire
License: MIT
Author: Carles Sala
Author-email: carles@pythiac.com
Requires-Python: >=3.7,<4.0
Classifier: Development Status :: 1 - Planning
Classifier: License :: OSI Approved :: MIT License
Classifier: Programming Language :: Python :: 3
Classifier: Programming Language :: Python :: 3.10
Classifier: Programming Language :: Python :: 3.7
Classifier: Programming Language :: Python :: 3.8
Classifier: Programming Language :: Python :: 3.9
Requires-Dist: click (>=8.0.1)
Project-URL: Changelog, https://github.com/csala/saffire/releases
Project-URL: Documentation, https://saffire.readthedocs.io
Project-URL: Repository, https://github.com/csala/saffire
